xepto50/__init__.py
xepto50/__main__.py
xepto50/cal.py
xepto50/gui.py
xepto50/run.py
xepto50/utils/__init__.py
xepto50/utils/curve_fitting.py
xepto50/utils/plots.py
xepto50/utils/scores.py
xepto50/utils/utils.py
xepto50-0.0.2.dist-info/LICENSE
xepto50-0.0.2.dist-info/METADATA
xepto50-0.0.2.dist-info/WHEEL
xepto50-0.0.2.dist-info/entry_points.txt
xepto50-0.0.2.dist-info/top_level.txt
xepto50-0.0.2.dist-info/RECORD
