Metadata-Version: 2.1
Name: xepto50
Version: 0.0.2
Summary: Calculate drug sensitivity in batch mode!
Home-page: https://www.kazilab.se
Author: Julhash Kazi
Author-email: xepto50@kazilab.se
License: Apache-2.0
Platform: any
License-File: LICENSE
Requires-Dist: IPython
Requires-Dist: matplotlib
Requires-Dist: numpy
Requires-Dist: scipy
Requires-Dist: pandas
Requires-Dist: scikit-learn
Requires-Dist: lmfit
Provides-Extra: gui
Requires-Dist: PyQt5 ; extra == 'gui'
